dumpo/__init__.py
dumpo/dumpo.py
dumpo/whoami.py
dumpo-0.0.8.dist-info/LICENSE
dumpo-0.0.8.dist-info/METADATA
dumpo-0.0.8.dist-info/WHEEL
dumpo-0.0.8.dist-info/top_level.txt
dumpo-0.0.8.dist-info/RECORD
