Metadata-Version: 2.1
Name: dumpo
Version: 0.0.8
Summary: Dumpo Python Object Serialiser
Home-page: https://github.com/jackyko8/dumpo
Author: Jacky Ko
Author-email: jko@accsoft.com.au
License: UNKNOWN
Project-URL: Bug Tracker, https://github.com/jackyko8/dumpo/issues
Platform: UNKNOWN
Classifier: Programming Language :: Python :: 3
Classifier: License :: OSI Approved :: MIT License
Classifier: Operating System :: OS Independent
Requires-Python: >=3.6
License-File: LICENSE
